nats_jwt/__init__.py
nats_jwt/nkeys_ext/__init__.py
nats_jwt/nkeys_ext/nkeys2.py
nats_jwt/v2/__init__.py
nats_jwt/v2/account_claims.py
nats_jwt/v2/claims.py
nats_jwt/v2/common.py
nats_jwt/v2/decoder.py
nats_jwt/v2/header.py
nats_jwt/v2/operator_claims.py
nats_jwt/v2/revocation_list.py
nats_jwt/v2/signing_keys.py
nats_jwt/v2/snippets.py
nats_jwt/v2/types.py
nats_jwt/v2/user_claims.py
nats_jwt/v2/validation.py
nats_jwt/v2/version.py
nats_jwt-0.2.2.dist-info/LICENSE
nats_jwt-0.2.2.dist-info/METADATA
nats_jwt-0.2.2.dist-info/WHEEL
nats_jwt-0.2.2.dist-info/RECORD
