Metadata-Version: 2.3
Name: nats-jwt
Version: 0.2.2
Summary: NATS JWT tokens signed using NKeys for the Python3 ecosystem
License: Apache-2.0
Author: Seznam.cz, a.s.
Author-email: cdn.vyvoj@firma.seznam.cz
Requires-Python: >=3.9,<4.0
Classifier: License :: OSI Approved :: Apache Software License
Classifier: Programming Language :: Python :: 3
Classifier: Programming Language :: Python :: 3.9
Classifier: Programming Language :: Python :: 3.10
Classifier: Programming Language :: Python :: 3.11
Classifier: Programming Language :: Python :: 3.12
Classifier: Programming Language :: Python :: 3.13
Requires-Dist: dacite (>=1.8.1,<2.0.0)
Requires-Dist: dataclasses-json (>=0.6.4,<0.7.0)
Requires-Dist: nkeys (>=0.2.1,<0.3.0)
Requires-Dist: pycryptodome (>=3.20.0,<4.0.0)
Requires-Dist: pytz (>=2024.1,<2025.0)
